bibliomorph/__init__.py
bibliomorph/graph.py
bibliomorph/py.typed
bibliomorph/types.py
bibliomorph/formatters/__init__.py
bibliomorph/formatters/formatter.py
bibliomorph/formatters/mapping.py
bibliomorph/loaders/__init__.py
bibliomorph/loaders/bibtex.py
bibliomorph/loaders/csl.py
bibliomorph/loaders/excel_attribute.py
bibliomorph/loaders/excel_links.py
bibliomorph/loaders/excel_matrix.py
bibliomorph/loaders/loader.py
bibliomorph/loaders/snowball.py
bibliomorph/loaders/table_attribute.py
bibliomorph/loaders/table_links.py
bibliomorph/matchers/__init__.py
bibliomorph/matchers/matcher.py
bibliomorph/matchers/text.py
bibliomorph/processors/__init__.py
bibliomorph/processors/crossref.py
bibliomorph/processors/deduplicater.py
bibliomorph/processors/openalex.py
bibliomorph/processors/processor.py
bibliomorph/utils/formatting.py
bibliomorph/utils/string.py
bibliomorph-0.1.2.dist-info/METADATA
bibliomorph-0.1.2.dist-info/WHEEL
bibliomorph-0.1.2.dist-info/RECORD
