Metadata-Version: 2.4
Name: bibliomorph
Version: 0.1.2
Summary: Add your description here
Author-email: Shengchen Zhang <hello@shengchen.io>
Requires-Python: >=3.10
Requires-Dist: citeproc-py>=0.9.0
Requires-Dist: clean-text>=0.6.0
Requires-Dist: crossrefapi>=1.7.0
Requires-Dist: dpath>=2.2.0
Requires-Dist: loguru>=0.7.3
Requires-Dist: more-itertools>=10.8.0
Requires-Dist: networkx>=3.4.2
Requires-Dist: openpyxl>=3.1.5
Requires-Dist: pandas>=2.3.3
Requires-Dist: pyalex>=0.19
Requires-Dist: rapidfuzz>=3.14.3
Requires-Dist: scipy>=1.15.3
